mxqq_snakesay-1.0.0.dist-info/licenses/LICENSE
snakesay/__init__.py
snakesay/__main__.py
snakesay/snake.py
mxqq_snakesay-1.0.0.dist-info/METADATA
mxqq_snakesay-1.0.0.dist-info/WHEEL
mxqq_snakesay-1.0.0.dist-info/entry_points.txt
mxqq_snakesay-1.0.0.dist-info/top_level.txt
mxqq_snakesay-1.0.0.dist-info/RECORD
