Metadata-Version: 2.4
Name: mxqq-snakesay
Version: 1.0.0
Summary: A fun command line tool that makes a snake say things
Author-email: mxqq <moxinqian_vip@163.com>
License: MIT License
Classifier: Programming Language :: Python :: 3
Classifier: License :: OSI Approved :: MIT License
Classifier: Operating System :: OS Independent
Requires-Python: >=3.7
License-File: LICENSE
Dynamic: license-file
